{
  "address": "0xe3594ef66b734e2879c46f90e322013548bd5beb",
  "type": "ERC721",
  "name": "Ikaro Cavalcante (occulted)",
  "tokenCount": "1",
  "uri": "https://arweave.net/Kci-km_f31FBiikYG93mO1E9zKiko0S4l3gLv6JkZHM",
  "metadata": {
    "name": "Intuitive Freedom",
    "created_by": "Ikaro Cavalcante (occulted)",
    "external_url": "https://arweave.net/mMl2IOzPfoOolpTmOL6WkUyU9vpKPtNvrXEnKkibrLM",
    "description": "Ikaro Cavalcante (occulted), 2022.\n\n\"Intuitive Freedom\"  \n \nWith “Intuitive Freedom” we are presented with a landscape slightly bathed by the light of a central figure, a fountain-like fissure between desire and free will, mixing shades and shapes inviting us to release the grip which we tightened ourselves. The source that grants the work it’s smooth illumination also lights the shift in Ikaro’s own perception of their process, once felt imprisoned by their constant use of red and purple, is now clear that this is a path laid by their intuition since infancy, and that it gives an outline, not a barrier, to their world. With every step taken,  Cavalcante’s deep energetic connections assures with certainty that what we cannot see but feel guides their affections into art, and our eyes to a swing in details fine crafted. A still motion telling a story of inner freedom.  \n \nDimension: 3840 x 2160 pixels (4K)  \nFormat: .png\n\nMinted on the artist manifold smartcontract  \nListed on Institut\n\nhttps://institut.co/artwork/intuitive-freedom/",
    "attributes": [
      {
        "trait_type": "Artist",
        "value": "occulted"
      },
      {
        "trait_type": "Format",
        "value": "png"
      },
      {
        "trait_type": "Dimension",
        "value": "3840 x 2160 pixels"
      }
    ],
    "image_details": {
      "bytes": 13469428,
      "format": "PNG",
      "sha256": "2e80e36af56a5021a53952855579c6799cfff160d6ac1aea668272afaa207c76",
      "width": 3840,
      "height": 2160
    },
    "image": "https://arweave.net/mMl2IOzPfoOolpTmOL6WkUyU9vpKPtNvrXEnKkibrLM",
    "image_url": "https://arweave.net/mMl2IOzPfoOolpTmOL6WkUyU9vpKPtNvrXEnKkibrLM"
  }
}